metricsGPT/__init__.py
metricsGPT/metricsGPT.py
metricsGPT/ui/.gitignore
metricsGPT/ui/README.md
metricsGPT/ui/build/android-chrome-192x192.png
metricsGPT/ui/build/android-chrome-512x512.png
metricsGPT/ui/build/apple-touch-icon.png
metricsGPT/ui/build/asset-manifest.json
metricsGPT/ui/build/favicon-16x16.png
metricsGPT/ui/build/favicon-32x32.png
metricsGPT/ui/build/favicon.ico
metricsGPT/ui/build/index.html
metricsGPT/ui/build/manifest.json
metricsGPT/ui/build/metricsGPT.png
metricsGPT/ui/build/robots.txt
metricsGPT/ui/build/static/css/main.15ac5a25.css
metricsGPT/ui/build/static/css/main.15ac5a25.css.map
metricsGPT/ui/build/static/js/453.63c4db86.chunk.js
metricsGPT/ui/build/static/js/453.63c4db86.chunk.js.map
metricsGPT/ui/build/static/js/main.ac3cb6f8.js
metricsGPT/ui/build/static/js/main.ac3cb6f8.js.LICENSE.txt
metricsGPT/ui/build/static/js/main.ac3cb6f8.js.map
metricsGPT/ui/package-lock.json
metricsGPT/ui/package.json
metricsGPT/ui/public/android-chrome-192x192.png
metricsGPT/ui/public/android-chrome-512x512.png
metricsGPT/ui/public/apple-touch-icon.png
metricsGPT/ui/public/favicon-16x16.png
metricsGPT/ui/public/favicon-32x32.png
metricsGPT/ui/public/favicon.ico
metricsGPT/ui/public/index.html
metricsGPT/ui/public/manifest.json
metricsGPT/ui/public/metricsGPT.png
metricsGPT/ui/public/robots.txt
metricsGPT/ui/src/App.css
metricsGPT/ui/src/App.tsx
metricsGPT/ui/src/index.tsx
metricsGPT/ui/src/react-app-env.d.ts
metricsGPT/ui/src/reportWebVitals.ts
metricsGPT/ui/tsconfig.json
metricsgpt-0.3.0.dist-info/LICENSE
metricsgpt-0.3.0.dist-info/METADATA
metricsgpt-0.3.0.dist-info/WHEEL
metricsgpt-0.3.0.dist-info/entry_points.txt
metricsgpt-0.3.0.dist-info/RECORD
