Metadata-Version: 2.3
Name: metricsgpt
Version: 0.3.0
Summary: MetricsGPT is a tool for generating PromQL queries from natural language queries. Talk to your metrics!
Home-page: https://github.com/saswatamcode/metricsgpt
License: Apache-2.0
Keywords: prometheus,promql,metrics,chat,llm,sre,observability
Author: Saswata Mukherjee
Author-email: saswataminsta@yahoo.com
Maintainer: Saswata Mukherjee
Maintainer-email: saswataminsta@yahoo.com
Requires-Python: >=3.12,<4.0
Classifier: License :: OSI Approved :: Apache Software License
Classifier: Programming Language :: Python :: 3
Classifier: Programming Language :: Python :: 3.12
Classifier: Programming Language :: Python :: 3.13
Requires-Dist: aioconsole (>=0.8.1,<0.9.0)
Requires-Dist: colorama (>=0.4.6,<0.5.0)
Requires-Dist: fastapi (>=0.115.6,<0.116.0)
Requires-Dist: llama-index (>=0.12.10,<0.13.0)
Requires-Dist: llama-index-embeddings-azure-openai (>=0.3.0,<0.4.0)
Requires-Dist: llama-index-embeddings-ollama (>=0.5.0,<0.6.0)
Requires-Dist: llama-index-llms-azure-openai (>=0.3.0,<0.4.0)
Requires-Dist: llama-index-llms-gemini (>=0.4.3,<0.5.0)
Requires-Dist: llama-index-llms-ollama (>=0.5.0,<0.6.0)
Requires-Dist: llama-index-vector-stores-milvus (>=0.5.0,<0.6.0)
Requires-Dist: prometheus-api-client (>=0.5.5,<0.6.0)
Requires-Dist: pyyaml (>=6.0.2,<7.0.0)
Requires-Dist: uvicorn (>=0.34.0,<0.35.0)
Project-URL: Documentation, https://github.com/saswatamcode/metricsgpt
Project-URL: Repository, https://github.com/saswatamcode/metricsgpt
